{
  "timestamp": "2026-04-03T11:26:21.845721",
  "total": 2,
  "sources": {
    "财联社电报": 0,
    "财联社财经": 0,
    "36氪": 5,
    "钛媒体": 0,
    "虎嗅": 2,
    "华尔街见闻": 0
  },
  "categories": {
    "finance": [],
    "industry": [],
    "tech": [],
    "byd": [],
    "tencent": [],
    "fitness": [],
    "other": [
      {
        "title": "耐克急需向臃肿库存开刀",
        "url": "https://www.huxiu.comhttps://www.huxiu.com/article/4847933.html",
        "source": "虎嗅",
        "time": "2026-04-03 11:26"
      },
      {
        "title": "张雪背后的那个人，让F1估值狂涨500%",
        "url": "https://www.huxiu.comhttps://www.huxiu.com/article/4847864.html",
        "source": "虎嗅",
        "time": "2026-04-03 11:26"
      }
    ]
  },
  "raw_news": [
    {
      "title": "耐克急需向臃肿库存开刀",
      "url": "https://www.huxiu.comhttps://www.huxiu.com/article/4847933.html",
      "source": "虎嗅",
      "time": "2026-04-03 11:26"
    },
    {
      "title": "张雪背后的那个人，让F1估值狂涨500%",
      "url": "https://www.huxiu.comhttps://www.huxiu.com/article/4847864.html",
      "source": "虎嗅",
      "time": "2026-04-03 11:26"
    }
  ]
}