{
  "timestamp": "2026-07-01T10:35:28.876961",
  "total": 5,
  "sources": {
    "财联社电报": 0,
    "财联社财经": 0,
    "36氪": 4,
    "钛媒体": 0,
    "虎嗅": 1,
    "华尔街见闻": 0
  },
  "categories": {
    "finance": [
      {
        "title": "北京计算光刻龙头要IPO了，拟募资25亿",
        "url": "https://36kr.com/p/3876903529771010",
        "source": "36氪",
        "time": "2026-07-01 10:35"
      }
    ],
    "industry": [],
    "tech": [],
    "byd": [],
    "tencent": [],
    "fitness": [],
    "other": [
      {
        "title": "关于「一人公司」的几句扎心实话：政策不包生儿子",
        "url": "https://36kr.com/p/3876890539290884",
        "source": "36氪",
        "time": "2026-07-01 10:35"
      },
      {
        "title": "一人公司真的是我的时代红利吗？",
        "url": "https://36kr.com/p/3876890539290884",
        "source": "36氪",
        "time": "2026-07-01 10:35"
      },
      {
        "title": "宇树“抱元守一”，智元“化整为零”",
        "url": "https://36kr.com/p/3876889696743680",
        "source": "36氪",
        "time": "2026-07-01 10:35"
      },
      {
        "title": "车企都说电池符合新国标，但没人敢写进合同",
        "url": "https://www.huxiu.comhttps://www.huxiu.com/article/4871814.html",
        "source": "虎嗅",
        "time": "2026-07-01 10:35"
      }
    ]
  },
  "raw_news": [
    {
      "title": "北京计算光刻龙头要IPO了，拟募资25亿",
      "url": "https://36kr.com/p/3876903529771010",
      "source": "36氪",
      "time": "2026-07-01 10:35"
    },
    {
      "title": "关于「一人公司」的几句扎心实话：政策不包生儿子",
      "url": "https://36kr.com/p/3876890539290884",
      "source": "36氪",
      "time": "2026-07-01 10:35"
    },
    {
      "title": "一人公司真的是我的时代红利吗？",
      "url": "https://36kr.com/p/3876890539290884",
      "source": "36氪",
      "time": "2026-07-01 10:35"
    },
    {
      "title": "宇树“抱元守一”，智元“化整为零”",
      "url": "https://36kr.com/p/3876889696743680",
      "source": "36氪",
      "time": "2026-07-01 10:35"
    },
    {
      "title": "车企都说电池符合新国标，但没人敢写进合同",
      "url": "https://www.huxiu.comhttps://www.huxiu.com/article/4871814.html",
      "source": "虎嗅",
      "time": "2026-07-01 10:35"
    }
  ]
}