{
  "timestamp": "2026-05-19T20:56:14.547631",
  "total": 7,
  "sources": {
    "财联社电报": 0,
    "财联社财经": 0,
    "36氪": 5,
    "钛媒体": 0,
    "虎嗅": 0,
    "华尔街见闻": 0
  },
  "categories": {
    "finance": [],
    "industry": [],
    "tech": [
      {
        "title": "红果取消部分AI仿真人剧本保底，出清垃圾产能",
        "url": "https://36kr.com/p/3816076557409793",
        "source": "36氪",
        "time": "2026-05-19 20:56"
      },
      {
        "title": "市场在狠狠惩罚不豪赌AI的国家、企业、个人",
        "url": "https://www.huxiu.comhttps://www.huxiu.com/article/4859688.html",
        "source": "虎嗅",
        "time": "2026-05-19 20:56"
      }
    ],
    "byd": [],
    "tencent": [],
    "fitness": [],
    "other": [
      {
        "title": "“疯狂”的石头与“消失”的CEO",
        "url": "https://36kr.com/p/3816140397633026",
        "source": "36氪",
        "time": "2026-05-19 20:56"
      },
      {
        "title": "骂完预制菜，年轻人还是不想进厨房",
        "url": "https://36kr.com/p/3816091319083265",
        "source": "36氪",
        "time": "2026-05-19 20:56"
      },
      {
        "title": "全民厌弃预制菜、消费重回理性，但“厨房经济”为何依然熄火？",
        "url": "https://36kr.com/p/3816091319083265",
        "source": "36氪",
        "time": "2026-05-19 20:56"
      },
      {
        "title": "红果短剧此举，其实是倒逼制作方演进。",
        "url": "https://36kr.com/p/3816076557409793",
        "source": "36氪",
        "time": "2026-05-19 20:56"
      },
      {
        "title": "《给阿嬷的情书》极可能是当下最重要的电影",
        "url": "https://www.huxiu.comhttps://www.huxiu.com/article/4859684.html",
        "source": "虎嗅",
        "time": "2026-05-19 20:56"
      }
    ]
  },
  "raw_news": [
    {
      "title": "“疯狂”的石头与“消失”的CEO",
      "url": "https://36kr.com/p/3816140397633026",
      "source": "36氪",
      "time": "2026-05-19 20:56"
    },
    {
      "title": "骂完预制菜，年轻人还是不想进厨房",
      "url": "https://36kr.com/p/3816091319083265",
      "source": "36氪",
      "time": "2026-05-19 20:56"
    },
    {
      "title": "全民厌弃预制菜、消费重回理性，但“厨房经济”为何依然熄火？",
      "url": "https://36kr.com/p/3816091319083265",
      "source": "36氪",
      "time": "2026-05-19 20:56"
    },
    {
      "title": "红果取消部分AI仿真人剧本保底，出清垃圾产能",
      "url": "https://36kr.com/p/3816076557409793",
      "source": "36氪",
      "time": "2026-05-19 20:56"
    },
    {
      "title": "红果短剧此举，其实是倒逼制作方演进。",
      "url": "https://36kr.com/p/3816076557409793",
      "source": "36氪",
      "time": "2026-05-19 20:56"
    },
    {
      "title": "市场在狠狠惩罚不豪赌AI的国家、企业、个人",
      "url": "https://www.huxiu.comhttps://www.huxiu.com/article/4859688.html",
      "source": "虎嗅",
      "time": "2026-05-19 20:56"
    },
    {
      "title": "《给阿嬷的情书》极可能是当下最重要的电影",
      "url": "https://www.huxiu.comhttps://www.huxiu.com/article/4859684.html",
      "source": "虎嗅",
      "time": "2026-05-19 20:56"
    }
  ]
}