{
  "timestamp": "2026-05-12T10:44:25.210401",
  "total": 7,
  "sources": {
    "财联社电报": 0,
    "财联社财经": 0,
    "36氪": 5,
    "钛媒体": 0,
    "虎嗅": 2,
    "华尔街见闻": 0
  },
  "categories": {
    "finance": [],
    "industry": [
      {
        "title": "葛仙村NPC“小黄鱼”公开道歉后，游客反而更爱他？",
        "url": "https://36kr.com/p/3806059216461314",
        "source": "36氪",
        "time": "2026-05-12 10:44"
      }
    ],
    "tech": [
      {
        "title": "只有 30 万像素的「AI 桌宠」卖爆了，凭什么？",
        "url": "https://36kr.com/p/3806113176608260",
        "source": "36氪",
        "time": "2026-05-12 10:44"
      },
      {
        "title": "借一百年后的钱，造看不懂的AI",
        "url": "https://www.huxiu.comhttps://www.huxiu.com/article/4857638.html",
        "source": "虎嗅",
        "time": "2026-05-12 10:44"
      }
    ],
    "byd": [],
    "tencent": [],
    "fitness": [],
    "other": [
      {
        "title": "“心血管龙头”信立泰再次跌停，核心产品发布临床进展带崩股价？",
        "url": "https://36kr.com/p/3806042998267656",
        "source": "36氪",
        "time": "2026-05-12 10:44"
      },
      {
        "title": "老牌仿制药企转型创新药",
        "url": "https://36kr.com/p/3806042998267656",
        "source": "36氪",
        "time": "2026-05-12 10:44"
      },
      {
        "title": "一场由道歉引发的景区体验“革命”",
        "url": "https://36kr.com/p/3806059216461314",
        "source": "36氪",
        "time": "2026-05-12 10:44"
      },
      {
        "title": "随特朗普访华的高管们都怎么飞北京",
        "url": "https://www.huxiu.comhttps://www.huxiu.com/article/4857620.html",
        "source": "虎嗅",
        "time": "2026-05-12 10:44"
      }
    ]
  },
  "raw_news": [
    {
      "title": "“心血管龙头”信立泰再次跌停，核心产品发布临床进展带崩股价？",
      "url": "https://36kr.com/p/3806042998267656",
      "source": "36氪",
      "time": "2026-05-12 10:44"
    },
    {
      "title": "老牌仿制药企转型创新药",
      "url": "https://36kr.com/p/3806042998267656",
      "source": "36氪",
      "time": "2026-05-12 10:44"
    },
    {
      "title": "葛仙村NPC“小黄鱼”公开道歉后，游客反而更爱他？",
      "url": "https://36kr.com/p/3806059216461314",
      "source": "36氪",
      "time": "2026-05-12 10:44"
    },
    {
      "title": "一场由道歉引发的景区体验“革命”",
      "url": "https://36kr.com/p/3806059216461314",
      "source": "36氪",
      "time": "2026-05-12 10:44"
    },
    {
      "title": "只有 30 万像素的「AI 桌宠」卖爆了，凭什么？",
      "url": "https://36kr.com/p/3806113176608260",
      "source": "36氪",
      "time": "2026-05-12 10:44"
    },
    {
      "title": "借一百年后的钱，造看不懂的AI",
      "url": "https://www.huxiu.comhttps://www.huxiu.com/article/4857638.html",
      "source": "虎嗅",
      "time": "2026-05-12 10:44"
    },
    {
      "title": "随特朗普访华的高管们都怎么飞北京",
      "url": "https://www.huxiu.comhttps://www.huxiu.com/article/4857620.html",
      "source": "虎嗅",
      "time": "2026-05-12 10:44"
    }
  ]
}