{
  "timestamp": "2026-06-01T02:08:27.727484",
  "total": 7,
  "sources": {
    "财联社电报": 0,
    "财联社财经": 0,
    "36氪": 5,
    "钛媒体": 0,
    "虎嗅": 2,
    "华尔街见闻": 0
  },
  "categories": {
    "finance": [
      {
        "title": "中国两大AI“妖股”，杀回A股",
        "url": "https://www.huxiu.comhttps://www.huxiu.com/article/4863217.html",
        "source": "虎嗅",
        "time": "2026-06-01 02:08"
      }
    ],
    "industry": [],
    "tech": [],
    "byd": [],
    "tencent": [],
    "fitness": [],
    "other": [
      {
        "title": "日本入境游当下最需要回答的问题，不是那些创新高的数字能否维持到下个季度",
        "url": "https://36kr.com/p/3829584131843461",
        "source": "36氪",
        "time": "2026-06-01 02:08"
      },
      {
        "title": "苏州来了个“海归” 中海单价破纪录拿下苏州工业园地块",
        "url": "https://36kr.com/p/3833969553074052",
        "source": "36氪",
        "time": "2026-06-01 02:08"
      },
      {
        "title": "此次拿地，是中海2026年以来在苏州的首次出手，也是其自2021年竞得超塔地块后，时隔五年再次回到其最熟悉的苏州工业园区土地市场。",
        "url": "https://36kr.com/p/3833969553074052",
        "source": "36氪",
        "time": "2026-06-01 02:08"
      },
      {
        "title": "书记市长“问计”，这条走廊有多重要？",
        "url": "https://36kr.com/p/3833970019657344",
        "source": "36氪",
        "time": "2026-06-01 02:08"
      },
      {
        "title": "科创策源地、产业隆起带和经济增长极",
        "url": "https://36kr.com/p/3833970019657344",
        "source": "36氪",
        "time": "2026-06-01 02:08"
      },
      {
        "title": "欧盟“开疆扩土”的新思路",
        "url": "https://www.huxiu.comhttps://www.huxiu.com/article/4863194.html",
        "source": "虎嗅",
        "time": "2026-06-01 02:08"
      }
    ]
  },
  "raw_news": [
    {
      "title": "日本入境游当下最需要回答的问题，不是那些创新高的数字能否维持到下个季度",
      "url": "https://36kr.com/p/3829584131843461",
      "source": "36氪",
      "time": "2026-06-01 02:08"
    },
    {
      "title": "苏州来了个“海归” 中海单价破纪录拿下苏州工业园地块",
      "url": "https://36kr.com/p/3833969553074052",
      "source": "36氪",
      "time": "2026-06-01 02:08"
    },
    {
      "title": "此次拿地，是中海2026年以来在苏州的首次出手，也是其自2021年竞得超塔地块后，时隔五年再次回到其最熟悉的苏州工业园区土地市场。",
      "url": "https://36kr.com/p/3833969553074052",
      "source": "36氪",
      "time": "2026-06-01 02:08"
    },
    {
      "title": "书记市长“问计”，这条走廊有多重要？",
      "url": "https://36kr.com/p/3833970019657344",
      "source": "36氪",
      "time": "2026-06-01 02:08"
    },
    {
      "title": "科创策源地、产业隆起带和经济增长极",
      "url": "https://36kr.com/p/3833970019657344",
      "source": "36氪",
      "time": "2026-06-01 02:08"
    },
    {
      "title": "欧盟“开疆扩土”的新思路",
      "url": "https://www.huxiu.comhttps://www.huxiu.com/article/4863194.html",
      "source": "虎嗅",
      "time": "2026-06-01 02:08"
    },
    {
      "title": "中国两大AI“妖股”，杀回A股",
      "url": "https://www.huxiu.comhttps://www.huxiu.com/article/4863217.html",
      "source": "虎嗅",
      "time": "2026-06-01 02:08"
    }
  ]
}