{
  "timestamp": "2026-04-14T15:51:25.912165",
  "total": 6,
  "sources": {
    "财联社电报": 0,
    "财联社财经": 0,
    "36氪": 4,
    "钛媒体": 0,
    "虎嗅": 2,
    "华尔街见闻": 0
  },
  "categories": {
    "finance": [],
    "industry": [],
    "tech": [
      {
        "title": "微软想给所有 Windows 电脑预装龙虾",
        "url": "https://36kr.com/p/3766613357543936",
        "source": "36氪",
        "time": "2026-04-14 15:50"
      },
      {
        "title": "AI电荒突围：谁能替代重燃？",
        "url": "https://www.huxiu.comhttps://www.huxiu.com/article/4850509.html",
        "source": "虎嗅",
        "time": "2026-04-14 15:51"
      }
    ],
    "byd": [],
    "tencent": [],
    "fitness": [],
    "other": [
      {
        "title": "网易互娱架构调整，市场负责人王怡调任海外",
        "url": "https://36kr.com/p/3766722584822537",
        "source": "36氪",
        "time": "2026-04-14 15:50"
      },
      {
        "title": "网易否认王怡离职，称其调任海外，市场中心更名。",
        "url": "https://36kr.com/p/3766722584822537",
        "source": "36氪",
        "time": "2026-04-14 15:50"
      },
      {
        "title": "后端是 Copilot 哟",
        "url": "https://36kr.com/p/3766613357543936",
        "source": "36氪",
        "time": "2026-04-14 15:50"
      },
      {
        "title": "游戏股暴跌，能关注了吗？",
        "url": "https://www.huxiu.comhttps://www.huxiu.com/article/4850499.html",
        "source": "虎嗅",
        "time": "2026-04-14 15:51"
      }
    ]
  },
  "raw_news": [
    {
      "title": "网易互娱架构调整，市场负责人王怡调任海外",
      "url": "https://36kr.com/p/3766722584822537",
      "source": "36氪",
      "time": "2026-04-14 15:50"
    },
    {
      "title": "网易否认王怡离职，称其调任海外，市场中心更名。",
      "url": "https://36kr.com/p/3766722584822537",
      "source": "36氪",
      "time": "2026-04-14 15:50"
    },
    {
      "title": "微软想给所有 Windows 电脑预装龙虾",
      "url": "https://36kr.com/p/3766613357543936",
      "source": "36氪",
      "time": "2026-04-14 15:50"
    },
    {
      "title": "后端是 Copilot 哟",
      "url": "https://36kr.com/p/3766613357543936",
      "source": "36氪",
      "time": "2026-04-14 15:50"
    },
    {
      "title": "游戏股暴跌，能关注了吗？",
      "url": "https://www.huxiu.comhttps://www.huxiu.com/article/4850499.html",
      "source": "虎嗅",
      "time": "2026-04-14 15:51"
    },
    {
      "title": "AI电荒突围：谁能替代重燃？",
      "url": "https://www.huxiu.comhttps://www.huxiu.com/article/4850509.html",
      "source": "虎嗅",
      "time": "2026-04-14 15:51"
    }
  ]
}