{
  "timestamp": "2026-05-19T08:54:32.798541",
  "total": 7,
  "sources": {
    "财联社电报": 0,
    "财联社财经": 0,
    "36氪": 5,
    "钛媒体": 0,
    "虎嗅": 2,
    "华尔街见闻": 0
  },
  "categories": {
    "finance": [],
    "industry": [],
    "tech": [
      {
        "title": "670 亿美元，AI 崛起，促成美国最大能源并购案",
        "url": "https://36kr.com/p/3815702503808512",
        "source": "36氪",
        "time": "2026-05-19 08:54"
      },
      {
        "title": "​GPU 烧算力，电网烧钱，最后是普通消费者买单。",
        "url": "https://36kr.com/p/3815702503808512",
        "source": "36氪",
        "time": "2026-05-19 08:54"
      }
    ],
    "byd": [],
    "tencent": [],
    "fitness": [],
    "other": [
      {
        "title": "亚洲最贵离婚新进展，SK海力士员工成相亲顶流，老板离婚要分73亿？",
        "url": "https://36kr.com/p/3815697664859655",
        "source": "36氪",
        "time": "2026-05-19 08:54"
      },
      {
        "title": "隐忍18年的前妻，是时候分红利了。",
        "url": "https://36kr.com/p/3815697664859655",
        "source": "36氪",
        "time": "2026-05-19 08:54"
      },
      {
        "title": "蜜雪冰城开始卖酒：打酒铺的老生意，又翻红了？",
        "url": "https://36kr.com/p/3815697518157315",
        "source": "36氪",
        "time": "2026-05-19 08:54"
      },
      {
        "title": "关于连续两篇文章被删除的说明",
        "url": "https://www.huxiu.comhttps://www.huxiu.com/article/4859569.html",
        "source": "虎嗅",
        "time": "2026-05-19 08:54"
      },
      {
        "title": "无限流已经是内容市场的奶皮子了",
        "url": "https://www.huxiu.comhttps://www.huxiu.com/article/4859555.html",
        "source": "虎嗅",
        "time": "2026-05-19 08:54"
      }
    ]
  },
  "raw_news": [
    {
      "title": "亚洲最贵离婚新进展，SK海力士员工成相亲顶流，老板离婚要分73亿？",
      "url": "https://36kr.com/p/3815697664859655",
      "source": "36氪",
      "time": "2026-05-19 08:54"
    },
    {
      "title": "隐忍18年的前妻，是时候分红利了。",
      "url": "https://36kr.com/p/3815697664859655",
      "source": "36氪",
      "time": "2026-05-19 08:54"
    },
    {
      "title": "蜜雪冰城开始卖酒：打酒铺的老生意，又翻红了？",
      "url": "https://36kr.com/p/3815697518157315",
      "source": "36氪",
      "time": "2026-05-19 08:54"
    },
    {
      "title": "670 亿美元，AI 崛起，促成美国最大能源并购案",
      "url": "https://36kr.com/p/3815702503808512",
      "source": "36氪",
      "time": "2026-05-19 08:54"
    },
    {
      "title": "​GPU 烧算力，电网烧钱，最后是普通消费者买单。",
      "url": "https://36kr.com/p/3815702503808512",
      "source": "36氪",
      "time": "2026-05-19 08:54"
    },
    {
      "title": "关于连续两篇文章被删除的说明",
      "url": "https://www.huxiu.comhttps://www.huxiu.com/article/4859569.html",
      "source": "虎嗅",
      "time": "2026-05-19 08:54"
    },
    {
      "title": "无限流已经是内容市场的奶皮子了",
      "url": "https://www.huxiu.comhttps://www.huxiu.com/article/4859555.html",
      "source": "虎嗅",
      "time": "2026-05-19 08:54"
    }
  ]
}